bdd/__init__.py
bdd/__main__.py
bdd/bddconfig.py
bdd/bddio.py
bdd/bddservice.py
bdd/bddsubprocess.py
bdd/bootdevcliconfig.py
bdd/cli.py
bdd/client.py
bdd/commands.py
bdd/lesson.py
bdd/progress.py
bddcmd-1.0.1.dist-info/LICENSE
bddcmd-1.0.1.dist-info/METADATA
bddcmd-1.0.1.dist-info/WHEEL
bddcmd-1.0.1.dist-info/entry_points.txt
bddcmd-1.0.1.dist-info/top_level.txt
bddcmd-1.0.1.dist-info/RECORD
