Metadata-Version: 2.1
Name: bddcmd
Version: 1.0.1
Summary: A CLI tool for completing boot.dev lessons
Author-email: Casey Woolfolk <ccwoolfolk@gmail.com>
Project-URL: Homepage, https://github.com/ccwoolfolk/bdd
Project-URL: Issues, https://github.com/ccwoolfolk/bdd/issues
Requires-Python: >=3.10
License-File: LICENSE
Requires-Dist: click>=8.1
Requires-Dist: requests>=2.32
Requires-Dist: PyYAML>=6.0
Requires-Dist: websocket-client>=1.8
Provides-Extra: dev
Requires-Dist: black; extra == "dev"
Requires-Dist: pytest; extra == "dev"
Requires-Dist: pytest-cov; extra == "dev"
Requires-Dist: mypy-extensions; extra == "dev"
